polyquack_django/__init__.py
polyquack_django/ariadne_decorators.py
polyquack_django/forms/widgets.py
polyquack_django/mixins.py
polyquack_django/templatetags/__init__.py
polyquack_django/templatetags/translate_filters.py
polyquack_django-0.2.dist-info/WHEEL
polyquack_django-0.2.dist-info/METADATA
polyquack_django-0.2.dist-info/RECORD
